sets/__init__.py
sets/config.py
xbyter_common-0.3.18.dist-info/METADATA
xbyter_common-0.3.18.dist-info/WHEEL
xbyter_common-0.3.18.dist-info/top_level.txt
xbyter_common-0.3.18.dist-info/RECORD
