Metadata-Version: 2.4
Name: xbyter_common
Version: 0.3.18
Summary: Common config and utilities for Xbyter projects
Author: xbyter
Author-email: amorcc@163.com
Requires-Python: >=3.11.9
Requires-Dist: pydantic-settings>=2.0.0
Requires-Dist: python-dotenv>=1.0.0
Dynamic: author
Dynamic: author-email
Dynamic: requires-dist
Dynamic: requires-python
Dynamic: summary
